avb/__init__.py
avb/attributes.py
avb/bin.py
avb/components.py
avb/core.py
avb/essence.py
avb/file.py
avb/interpolation.py
avb/ioctx.py
avb/misc.py
avb/mobid.py
avb/parameter_uuids.py
avb/trackgroups.py
avb/utils.py
pyavb-1.4.0.dist-info/LICENSE
pyavb-1.4.0.dist-info/METADATA
pyavb-1.4.0.dist-info/WHEEL
pyavb-1.4.0.dist-info/top_level.txt
pyavb-1.4.0.dist-info/RECORD
